{"cameraMode":{"drawMode":0,"name":"Shaded","section":"Shading Mode"},"sceneLighting":false,"audioPlay":false,"sceneViewState":{"m_AlwaysRefresh":false,"showFog":true,"showSkybox":false,"showFlares":true,"showImageEffects":true,"showParticleSystems":true,"showVisualEffectGraphs":true,"m_FxEnabled":true},"in2DMode":false,"pivot":{"x":19.897674560546876,"y":-4.1530985832214359,"z":12.93997859954834},"rotation":{"x":-0.010904227383434773,"y":-0.46601682901382449,"z":0.005707850214093924,"w":-0.8847131133079529},"size":32.87864303588867,"orthographic":false}